csle_cyborg/__init__.py
csle_cyborg/__version__.py
csle_cyborg/main.py
csle_cyborg/agents/__init__.py
csle_cyborg/agents/_demo_agents.py
csle_cyborg/agents/training_example.py
csle_cyborg/agents/simple_agents/__init__.py
csle_cyborg/agents/simple_agents/_demo_blue.py
csle_cyborg/agents/simple_agents/_demo_red.py
csle_cyborg/agents/simple_agents/b_line.py
csle_cyborg/agents/simple_agents/base_agent.py
csle_cyborg/agents/simple_agents/blue_load_agent.py
csle_cyborg/agents/simple_agents/blue_monitor_agent.py
csle_cyborg/agents/simple_agents/blue_react_agent.py
csle_cyborg/agents/simple_agents/counter_kill_chain_agent.py
csle_cyborg/agents/simple_agents/debugging_agent.py
csle_cyborg/agents/simple_agents/green_agent.py
csle_cyborg/agents/simple_agents/heuristic_red.py
csle_cyborg/agents/simple_agents/keyboard_agent.py
csle_cyborg/agents/simple_agents/killchain_agent.py
csle_cyborg/agents/simple_agents/meander.py
csle_cyborg/agents/simple_agents/sleep_agent.py
csle_cyborg/agents/simple_agents/test_agent.py
csle_cyborg/agents/simple_agents/test_flat_fixed.py
csle_cyborg/agents/simple_agents/test_keyboard_blue.py
csle_cyborg/agents/simple_agents/test_keyboard_red.py
csle_cyborg/agents/simple_agents/test_table_wrapper.py
csle_cyborg/agents/wrappers/__init__.py
csle_cyborg/agents/wrappers/base_wrapper.py
csle_cyborg/agents/wrappers/blue_table_wrapper.py
csle_cyborg/agents/wrappers/challenge_wrapper.py
csle_cyborg/agents/wrappers/enum_action_wrapper.py
csle_cyborg/agents/wrappers/fixed_flat_wrapper.py
csle_cyborg/agents/wrappers/int_list_to_action.py
csle_cyborg/agents/wrappers/open_ai_gym_wrapper.py
csle_cyborg/agents/wrappers/red_table_wrapper.py
csle_cyborg/agents/wrappers/reduce_action_space_wrapper.py
csle_cyborg/agents/wrappers/reward_shape.py
csle_cyborg/agents/wrappers/true_table_wrapper.py
csle_cyborg/evaluation/__init__.py
csle_cyborg/evaluation/evaluation.py
csle_cyborg/profiler/__init__.py
csle_cyborg/profiler/profiler.py
csle_cyborg/profiler/wrapper_profiler.py
csle_cyborg-0.0.3.dist-info/METADATA
csle_cyborg-0.0.3.dist-info/WHEEL
csle_cyborg-0.0.3.dist-info/top_level.txt
csle_cyborg-0.0.3.dist-info/RECORD
